gldcswpy/__init__.py
gldcswpy/csw.py
gldcswpy-1.0.2.dist-info/METADATA
gldcswpy-1.0.2.dist-info/WHEEL
gldcswpy-1.0.2.dist-info/RECORD
