Metadata-Version: 2.1
Name: gldcswpy
Version: 1.0.2
Summary: Generalized Lambda Distribution in CSW Parametrization for Python
Home-page: https://github.com/KavyaAnnapareddy/gldcswpy
License: MIT
Keywords: gld
Author: Kavya Annapareddy
Author-email: annapareddy.kavya@gmail.com
Requires-Python: >=3.12,<4.0
Classifier: License :: OSI Approved :: MIT License
Classifier: Programming Language :: Python :: 3
Classifier: Programming Language :: Python :: 3.12
Classifier: Programming Language :: Python :: 3.13
Classifier: Topic :: Scientific/Engineering
Requires-Dist: matplotlib (>=3.10.0,<4.0.0)
Requires-Dist: pytest (>=7.4.0)
Requires-Dist: scipy (>=1.15.0,<2.0.0)
Requires-Dist: seaborn (>=0.13.2,<0.14.0)
Project-URL: Repository, https://github.com/KavyaAnnapareddy/gldcswpy
